Metadata-Version: 2.1
Name: sqlmodel
Version: 0.0.26
Summary: SQLModel, SQL databases in Python, designed for simplicity, compatibility, and robustness.
Author-Email: =?utf-8?q?Sebasti=C3=A1n_Ram=C3=ADrez?= <tiangolo@gmail.com>
Classifier: Development Status :: 4 - Beta
Classifier: Framework :: AsyncIO
Classifier: Intended Audience :: Developers
Classifier: Intended Audience :: Science/Research
Classifier: Intended Audience :: System Administrators
Classifier: License :: OSI Approved :: MIT License
Classifier: Programming Language :: Python :: 3 :: Only
Classifier: Programming Language :: Python :: 3.8
Classifier: Programming Language :: Python :: 3.9
Classifier: Programming Language :: Python :: 3.10
Classifier: Programming Language :: Python :: 3.11
Classifier: Programming Language :: Python :: 3.12
Classifier: Programming Language :: Python :: 3.13
Classifier: Topic :: Database
Classifier: Topic :: Database :: Database Engines/Servers
Classifier: Topic :: Internet
Classifier: Topic :: Internet :: WWW/HTTP :: HTTP Servers
Classifier: Topic :: Internet :: WWW/HTTP
Classifier: Typing :: Typed
Project-URL: Homepage, https://github.com/fastapi/sqlmodel
Project-URL: Documentation, https://sqlmodel.tiangolo.com
Project-URL: Repository, https://github.com/fastapi/sqlmodel
Project-URL: Issues, https://github.com/fastapi/sqlmodel/issues
Project-URL: Changelog, https://sqlmodel.tiangolo.com/release-notes/
Requires-Python: >=3.8
Requires-Dist: SQLAlchemy<2.1.0,>=2.0.14
Requires-Dist: pydantic<3.0.0,>=1.10.13
